db_integrations/__init__.py
db_integrations/firestore_cache.py
db_integrations/local_cache.py
llm_cache_test-0.1.0.dist-info/LICENSE.md
llm_cache_test-0.1.0.dist-info/METADATA
llm_cache_test-0.1.0.dist-info/WHEEL
llm_cache_test-0.1.0.dist-info/top_level.txt
llm_cache_test-0.1.0.dist-info/RECORD
