Metadata-Version: 2.1
Name: llm-cache-test
Version: 0.1.0
Summary: LLMCache is an open-source caching solution designed to operate seamlessly within your cloud infrastructure.
Author: Neural Bridge
License: Apache License 2.0
Classifier: Programming Language :: Python :: 3
Classifier: License :: OSI Approved :: Apache Software License
Classifier: Operating System :: OS Independent
Requires-Python: >=3.6
License-File: LICENSE.md
Requires-Dist: google-cloud (==0.34.0)
Requires-Dist: google-auth (==2.27.0)
